pylahman/__init__.py
pylahman/data/AllstarFull.parquet
pylahman/data/Appearances.parquet
pylahman/data/AwardsManagers.parquet
pylahman/data/AwardsPlayers.parquet
pylahman/data/AwardsShareManagers.parquet
pylahman/data/AwardsSharePlayers.parquet
pylahman/data/Batting.parquet
pylahman/data/BattingPost.parquet
pylahman/data/CollegePlaying.parquet
pylahman/data/Fielding.parquet
pylahman/data/FieldingOF.parquet
pylahman/data/FieldingOFsplit.parquet
pylahman/data/FieldingPost.parquet
pylahman/data/HallOfFame.parquet
pylahman/data/HomeGames.parquet
pylahman/data/Managers.parquet
pylahman/data/ManagersHalf.parquet
pylahman/data/Parks.parquet
pylahman/data/People.parquet
pylahman/data/Pitching.parquet
pylahman/data/PitchingPost.parquet
pylahman/data/Salaries.parquet
pylahman/data/Schools.parquet
pylahman/data/SeriesPost.parquet
pylahman/data/Teams.parquet
pylahman/data/TeamsFranchises.parquet
pylahman/data/TeamsHalf.parquet
pylahman-0.7.0.dist-info/METADATA
pylahman-0.7.0.dist-info/WHEEL
pylahman-0.7.0.dist-info/licenses/LICENSE
pylahman-0.7.0.dist-info/RECORD
