Metadata-Version: 2.4
Name: pylahman
Version: 0.7.0
Summary: Python Package for Sean Lahman's Baseball Database
Project-URL: Homepage, https://github.com/daviddalpiaz/pylahman
Project-URL: Issues, https://github.com/daviddalpiaz/pylahman/issues
Author-email: David Dalpiaz <dalpiaz2@illinois.edu>
License: MIT
License-File: LICENSE
Requires-Python: >=3.12
Requires-Dist: numpy>=2.4.0
Requires-Dist: pandas>=2.3.3
Requires-Dist: pyarrow>=22.0.0
